pysmo/__init__.py
pysmo/core/__init__.py
pysmo/core/sac/__init__.py
pysmo/core/sac/sacfunc.py
pysmo/core/sac/sacheader.py
pysmo/core/sac/sacheader.yml
pysmo/core/sac/sacio.py
pysmo/tools/__init__.py
pysmo/tools/noise/__init__.py
pysmo/tools/noise/peterson.py
pysmo-0.8.3.dist-info/LICENSE
pysmo-0.8.3.dist-info/METADATA
pysmo-0.8.3.dist-info/WHEEL
pysmo-0.8.3.dist-info/RECORD
