Metadata-Version: 2.1
Name: pysmo
Version: 0.8.3
Summary: Python module to read/write/manipulate SAC (Seismic Analysis Code) files
License: GPL-3.0-or-later
Author: Simon M. Lloyd
Author-email: simon@slloyd.net
Requires-Python: >=3.8,<3.12
Classifier: Development Status :: 5 - Production/Stable
Classifier: Intended Audience :: Science/Research
Classifier: License :: OSI Approved :: GNU General Public License v3 or later (GPLv3+)
Classifier: Operating System :: OS Independent
Classifier: Programming Language :: Python :: 3
Classifier: Programming Language :: Python :: 3.8
Classifier: Programming Language :: Python :: 3.9
Classifier: Programming Language :: Python :: 3.10
Classifier: Programming Language :: Python :: 3.11
Classifier: Topic :: Scientific/Engineering
Requires-Dist: PyYAML (>=5.3.1,<6.0.0)
Requires-Dist: matplotlib (>=3.3.3,<4.0.0)
Requires-Dist: numpy (>=1.19.4,<2.0.0)
Requires-Dist: pyproj (>=3.0.0,<4.0.0)
Requires-Dist: requests (>=2.25.1,<3.0.0)
Requires-Dist: scipy (>=1.5.4,<2.0.0)
Project-URL: Documentation, https://pysmo.readthedocs.io
